{"data":{"index":1,"total":1,"posts":[{"title":"试试用代码块在 Hexo 中插入实况照片","slug":"博客站点维护/Hexo/试试用代码块在 Hexo 中插入实况照片","date":"2026-04-14T20:01:27.000Z","updated":"2026-04-17T14:16:07.933Z","comments":true,"url":"p/da4ac563/","excerpt":"","description":"例行的插件推广文，不过这篇文章参杂了很多开发杂记","language":"zh-CN","keywords":null,"cover":"https://cdn.gallery.uuanqin.top/img/202604142323499.webp","images":["https://github-readme-stats.uuanqin.top/api/pin/?username=uuanqin&amp;repo=hexo-filter-live-photo","https://cdn.gallery.uuanqin.top/live_photo/cover/ezgif-5901921d3f722129260414.jpg","https://cdn.gallery.uuanqin.top/img/202604150122018.webp"],"categories":[{"name":"博客站点维护","slug":"博客站点维护","api":"api/categories/博客站点维护.json"},{"name":"Hexo","slug":"博客站点维护/Hexo","api":"api/categories/博客站点维护/Hexo.json"}],"tags":[{"name":"Hexo","slug":"Hexo","api":"api/tags/Hexo.json"},{"name":"动态图片","slug":"动态图片","api":"api/tags/动态图片.json"},{"name":"实况照片","slug":"实况照片","api":"api/tags/实况照片.json"},{"name":"Live Photo","slug":"Live-Photo","api":"api/tags/Live-Photo.json"}],"api":"api/posts/p/da4ac563.json"},{"title":"动态图片测试","slug":"阿-测试文章/动态图片测试","date":"2026-04-14T13:36:40.000Z","updated":"2026-04-20T07:11:53.479Z","comments":true,"url":"p/6338f82f/","excerpt":"","description":"用于测试插件 hexo-filter-live-photo","language":"zh-CN","keywords":null,"cover":"https://cdn.gallery.uuanqin.top/img/ezgif-5901921d3f722129260414(1)dfsfdf.webp","images":["https://github-readme-stats.uuanqin.top/api/pin/?username=uuanqin&amp;repo=hexo-filter-live-photo","https://cdn.gallery.uuanqin.top/live_photo/cover/ezgif-5901921d3f722129260414.jpg","https://example.com/xxx/xxxxxx.jpg"],"categories":[{"name":"阿-测试文章","slug":"阿-测试文章","api":"api/categories/阿-测试文章.json"}],"tags":[{"name":"Hexo","slug":"Hexo","api":"api/tags/Hexo.json"},{"name":"动态图片","slug":"动态图片","api":"api/tags/动态图片.json"},{"name":"hexo-plugins","slug":"hexo-plugins","api":"api/tags/hexo-plugins.json"}],"api":"api/posts/p/6338f82f.json"}],"info":{"type":"tag","name":"动态图片","slug":"动态图片"}},"api":"api/tags/动态图片/page.1.json"}